mqresources/__init__.py
mqresources/mqutils.py
lts_mqemailnotifier-0.0.2.dist-info/METADATA
lts_mqemailnotifier-0.0.2.dist-info/WHEEL
lts_mqemailnotifier-0.0.2.dist-info/top_level.txt
lts_mqemailnotifier-0.0.2.dist-info/RECORD
