Metadata-Version: 2.1
Name: lts-mqemailnotifier
Version: 0.0.2
Summary: A set of utilities for placing a message onto a queue for an emailer listener to receive
Home-page: https://github.huit.harvard.edu/harvard-lts/mq_email_notifier
Author: Valdeva Crema
Author-email: valdeva_crema@harvard.edu
Classifier: Programming Language :: Python :: 3
Classifier: License :: OSI Approved :: MIT License
Classifier: Operating System :: OS Independent
Requires-Python: >=3.6
Requires-Dist: stomp.py (==8.0.1)
Requires-Dist: pytest
